README.md
setup.py
gpu_queuer/__init__.py
gpu_queuer/gpu_queuer.py
gpu_queuer/redis_client.py
gpu_queuer/redis_maintainer.py
gpu_queuer/utils.py
gpu_queuer.egg-info/PKG-INFO
gpu_queuer.egg-info/SOURCES.txt
gpu_queuer.egg-info/dependency_links.txt
gpu_queuer.egg-info/requires.txt
gpu_queuer.egg-info/top_level.txt