Metadata-Version: 2.1
Name: gpu-queuer
Version: 0.0.5
Summary: Deep learning tools
Home-page: https://github.com/deng1fan
Author: deng1fan
Author-email: dengyifan@iie.ac.cn
Keywords: gpu,queuer
Requires-Python: >=3.6
